{
    "ann": {
        "goal": [
            " go ",
            " to ",
            " the ",
            " drawer ",
            " and ",
            " pick ",
            " up ",
            " the ",
            " salt ",
            ". ",
            " then ",
            " go ",
            " to ",
            " the ",
            " living ",
            " room ",
            " and ",
            " place ",
            " the ",
            " salt ",
            " next ",
            " to ",
            " the ",
            " television ",
            ". ",
            "<<goal>>"
        ],
        "task_desc": "Go to the drawer and pick up the salt. Then go to the living room and place the salt next to the television."
    },
    "num": {
        "action_low": [
            {
                "base_action": 0,
                "grasp_drop": 0,
                "mode": 2,
                "state_ee": [
                    0,
                    0,
                    0
                ],
                "state_rot": [
                    143
                ],
                "up_down": 0
            },
            {
                "base_action": 4,
                "grasp_drop": 0,
                "mode": 1,
                "state_ee": [
                    0,
                    0,
                    0
                ],
                "state_rot": 0,
                "up_down": 0
            },
            {
                "base_action": 0,
                "grasp_drop": 0,
                "mode": 4,
                "state_ee": [
                    199,
                    135,
                    241
                ],
                "state_rot": 0,
                "up_down": 0
            },
            {
                "base_action": 0,
                "grasp_drop": 1,
                "mode": 5,
                "state_ee": [
                    0,
                    0,
                    0
                ],
                "state_rot": 0,
                "up_down": 0
            },
            {
                "base_action": 0,
                "grasp_drop": 0,
                "mode": 3,
                "state_ee": [
                    0,
                    0,
                    0
                ],
                "state_rot": 0,
                "up_down": 0
            },
            {
                "base_action": 0,
                "grasp_drop": 0,
                "mode": 4,
                "state_ee": [
                    117,
                    119,
                    145
                ],
                "state_rot": 0,
                "up_down": 0
            },
            {
                "base_action": 0,
                "grasp_drop": 0,
                "mode": 4,
                "state_ee": [
                    117,
                    119,
                    145
                ],
                "state_rot": 0,
                "up_down": 0
            },
            {
                "base_action": 0,
                "grasp_drop": 0,
                "mode": 4,
                "state_ee": [
                    117,
                    119,
                    144
                ],
                "state_rot": 0,
                "up_down": 0
            },
            {
                "base_action": 0,
                "grasp_drop": 0,
                "mode": 4,
                "state_ee": [
                    117,
                    119,
                    143
                ],
                "state_rot": 0,
                "up_down": 0
            },
            {
                "base_action": 0,
                "grasp_drop": 0,
                "mode": 4,
                "state_ee": [
                    117,
                    119,
                    142
                ],
                "state_rot": 0,
                "up_down": 0
            },
            {
                "base_action": 0,
                "grasp_drop": 0,
                "mode": 2,
                "state_ee": [
                    0,
                    0,
                    0
                ],
                "state_rot": [
                    136
                ],
                "up_down": 0
            },
            {
                "base_action": 0,
                "grasp_drop": 0,
                "mode": 2,
                "state_ee": [
                    0,
                    0,
                    0
                ],
                "state_rot": [
                    136
                ],
                "up_down": 0
            },
            {
                "base_action": 1,
                "grasp_drop": 0,
                "mode": 1,
                "state_ee": [
                    0,
                    0,
                    0
                ],
                "state_rot": 0,
                "up_down": 0
            },
            {
                "base_action": 1,
                "grasp_drop": 0,
                "mode": 1,
                "state_ee": [
                    0,
                    0,
                    0
                ],
                "state_rot": 0,
                "up_down": 0
            },
            {
                "base_action": 0,
                "grasp_drop": 0,
                "mode": 2,
                "state_ee": [
                    0,
                    0,
                    0
                ],
                "state_rot": [
                    136
                ],
                "up_down": 0
            },
            {
                "base_action": 0,
                "grasp_drop": 0,
                "mode": 2,
                "state_ee": [
                    0,
                    0,
                    0
                ],
                "state_rot": [
                    136
                ],
                "up_down": 0
            },
            {
                "base_action": 0,
                "grasp_drop": 0,
                "mode": 2,
                "state_ee": [
                    0,
                    0,
                    0
                ],
                "state_rot": [
                    136
                ],
                "up_down": 0
            },
            {
                "base_action": 0,
                "grasp_drop": 0,
                "mode": 2,
                "state_ee": [
                    0,
                    0,
                    0
                ],
                "state_rot": [
                    136
                ],
                "up_down": 0
            },
            {
                "base_action": 1,
                "grasp_drop": 0,
                "mode": 1,
                "state_ee": [
                    0,
                    0,
                    0
                ],
                "state_rot": 0,
                "up_down": 0
            },
            {
                "base_action": 1,
                "grasp_drop": 0,
                "mode": 1,
                "state_ee": [
                    0,
                    0,
                    0
                ],
                "state_rot": 0,
                "up_down": 0
            },
            {
                "base_action": 1,
                "grasp_drop": 0,
                "mode": 1,
                "state_ee": [
                    0,
                    0,
                    0
                ],
                "state_rot": 0,
                "up_down": 0
            },
            {
                "base_action": 1,
                "grasp_drop": 0,
                "mode": 1,
                "state_ee": [
                    0,
                    0,
                    0
                ],
                "state_rot": 0,
                "up_down": 0
            },
            {
                "base_action": 1,
                "grasp_drop": 0,
                "mode": 1,
                "state_ee": [
                    0,
                    0,
                    0
                ],
                "state_rot": 0,
                "up_down": 0
            },
            {
                "base_action": 1,
                "grasp_drop": 0,
                "mode": 1,
                "state_ee": [
                    0,
                    0,
                    0
                ],
                "state_rot": 0,
                "up_down": 0
            },
            {
                "base_action": 0,
                "grasp_drop": 0,
                "mode": 4,
                "state_ee": [
                    194,
                    136,
                    216
                ],
                "state_rot": 0,
                "up_down": 0
            },
            {
                "base_action": 0,
                "grasp_drop": 0,
                "mode": 4,
                "state_ee": [
                    116,
                    119,
                    148
                ],
                "state_rot": 0,
                "up_down": 0
            },
            {
                "base_action": 0,
                "grasp_drop": 0,
                "mode": 4,
                "state_ee": [
                    117,
                    119,
                    147
                ],
                "state_rot": 0,
                "up_down": 0
            },
            {
                "base_action": 0,
                "grasp_drop": 0,
                "mode": 4,
                "state_ee": [
                    117,
                    119,
                    146
                ],
                "state_rot": 0,
                "up_down": 0
            },
            {
                "base_action": 0,
                "grasp_drop": 0,
                "mode": 4,
                "state_ee": [
                    118,
                    119,
                    145
                ],
                "state_rot": 0,
                "up_down": 0
            },
            {
                "base_action": 0,
                "grasp_drop": 0,
                "mode": 4,
                "state_ee": [
                    118,
                    119,
                    145
                ],
                "state_rot": 0,
                "up_down": 0
            },
            {
                "base_action": 0,
                "grasp_drop": 0,
                "mode": 4,
                "state_ee": [
                    118,
                    119,
                    144
                ],
                "state_rot": 0,
                "up_down": 0
            },
            {
                "base_action": 0,
                "grasp_drop": 0,
                "mode": 4,
                "state_ee": [
                    118,
                    119,
                    143
                ],
                "state_rot": 0,
                "up_down": 0
            },
            {
                "base_action": 0,
                "grasp_drop": 0,
                "mode": 4,
                "state_ee": [
                    118,
                    119,
                    145
                ],
                "state_rot": 0,
                "up_down": 0
            },
            {
                "base_action": 2,
                "grasp_drop": 0,
                "mode": 1,
                "state_ee": [
                    0,
                    0,
                    0
                ],
                "state_rot": 0,
                "up_down": 0
            },
            {
                "base_action": 1,
                "grasp_drop": 0,
                "mode": 1,
                "state_ee": [
                    0,
                    0,
                    0
                ],
                "state_rot": 0,
                "up_down": 0
            },
            {
                "base_action": 3,
                "grasp_drop": 0,
                "mode": 1,
                "state_ee": [
                    0,
                    0,
                    0
                ],
                "state_rot": 0,
                "up_down": 0
            },
            {
                "base_action": 0,
                "grasp_drop": 0,
                "mode": 4,
                "state_ee": [
                    120,
                    119,
                    140
                ],
                "state_rot": 0,
                "up_down": 0
            },
            {
                "base_action": 0,
                "grasp_drop": 0,
                "mode": 4,
                "state_ee": [
                    119,
                    119,
                    143
                ],
                "state_rot": 0,
                "up_down": 0
            },
            {
                "base_action": 0,
                "grasp_drop": 0,
                "mode": 4,
                "state_ee": [
                    117,
                    119,
                    146
                ],
                "state_rot": 0,
                "up_down": 0
            },
            {
                "base_action": 4,
                "grasp_drop": 0,
                "mode": 1,
                "state_ee": [
                    0,
                    0,
                    0
                ],
                "state_rot": 0,
                "up_down": 0
            },
            {
                "base_action": 0,
                "grasp_drop": 0,
                "mode": 4,
                "state_ee": [
                    117,
                    119,
                    146
                ],
                "state_rot": 0,
                "up_down": 0
            },
            {
                "base_action": 0,
                "grasp_drop": 0,
                "mode": 4,
                "state_ee": [
                    117,
                    119,
                    146
                ],
                "state_rot": 0,
                "up_down": 0
            },
            {
                "base_action": 0,
                "grasp_drop": 0,
                "mode": 4,
                "state_ee": [
                    117,
                    119,
                    146
                ],
                "state_rot": 0,
                "up_down": 0
            },
            {
                "base_action": 0,
                "grasp_drop": 0,
                "mode": 4,
                "state_ee": [
                    117,
                    119,
                    146
                ],
                "state_rot": 0,
                "up_down": 0
            },
            {
                "base_action": 0,
                "grasp_drop": 0,
                "mode": 4,
                "state_ee": [
                    117,
                    119,
                    146
                ],
                "state_rot": 0,
                "up_down": 0
            },
            {
                "base_action": 1,
                "grasp_drop": 0,
                "mode": 1,
                "state_ee": [
                    0,
                    0,
                    0
                ],
                "state_rot": 0,
                "up_down": 0
            },
            {
                "base_action": 0,
                "grasp_drop": 0,
                "mode": 4,
                "state_ee": [
                    191,
                    136,
                    202
                ],
                "state_rot": 0,
                "up_down": 0
            },
            {
                "base_action": 2,
                "grasp_drop": 0,
                "mode": 1,
                "state_ee": [
                    0,
                    0,
                    0
                ],
                "state_rot": 0,
                "up_down": 0
            },
            {
                "base_action": 0,
                "grasp_drop": 0,
                "mode": 2,
                "state_ee": [
                    0,
                    0,
                    0
                ],
                "state_rot": [
                    125
                ],
                "up_down": 0
            },
            {
                "base_action": 0,
                "grasp_drop": 2,
                "mode": 5,
                "state_ee": [
                    0,
                    0,
                    0
                ],
                "state_rot": 0,
                "up_down": 0
            },
            {
                "base_action": 0,
                "grasp_drop": 0,
                "mode": 4,
                "state_ee": [
                    119,
                    119,
                    144
                ],
                "state_rot": 0,
                "up_down": 0
            },
            {
                "base_action": 0,
                "grasp_drop": 0,
                "mode": 4,
                "state_ee": [
                    117,
                    119,
                    146
                ],
                "state_rot": 0,
                "up_down": 0
            },
            {
                "base_action": 0,
                "grasp_drop": 0,
                "mode": 4,
                "state_ee": [
                    117,
                    119,
                    146
                ],
                "state_rot": 0,
                "up_down": 0
            },
            {
                "base_action": 0,
                "grasp_drop": 0,
                "mode": 4,
                "state_ee": [
                    117,
                    119,
                    146
                ],
                "state_rot": 0,
                "up_down": 0
            },
            {
                "base_action": 0,
                "grasp_drop": 0,
                "mode": 4,
                "state_ee": [
                    117,
                    119,
                    146
                ],
                "state_rot": 0,
                "up_down": 0
            },
            {
                "base_action": 0,
                "grasp_drop": 0,
                "mode": 4,
                "state_ee": [
                    117,
                    119,
                    146
                ],
                "state_rot": 0,
                "up_down": 0
            },
            {
                "base_action": 1,
                "grasp_drop": 0,
                "mode": 1,
                "state_ee": [
                    0,
                    0,
                    0
                ],
                "state_rot": 0,
                "up_down": 0
            },
            {
                "base_action": 0,
                "grasp_drop": 0,
                "mode": 4,
                "state_ee": [
                    190,
                    136,
                    204
                ],
                "state_rot": 0,
                "up_down": 0
            },
            {
                "base_action": 0,
                "grasp_drop": 0,
                "mode": 4,
                "state_ee": [
                    117,
                    119,
                    146
                ],
                "state_rot": 0,
                "up_down": 0
            },
            {
                "base_action": 0,
                "grasp_drop": 0,
                "mode": 4,
                "state_ee": [
                    117,
                    119,
                    146
                ],
                "state_rot": 0,
                "up_down": 0
            },
            {
                "base_action": 0,
                "grasp_drop": 0,
                "mode": 4,
                "state_ee": [
                    117,
                    119,
                    146
                ],
                "state_rot": 0,
                "up_down": 0
            },
            {
                "base_action": 0,
                "grasp_drop": 0,
                "mode": 4,
                "state_ee": [
                    117,
                    119,
                    146
                ],
                "state_rot": 0,
                "up_down": 0
            },
            {
                "base_action": 0,
                "grasp_drop": 0,
                "mode": 4,
                "state_ee": [
                    117,
                    119,
                    146
                ],
                "state_rot": 0,
                "up_down": 0
            },
            {
                "base_action": 0,
                "grasp_drop": 0,
                "mode": 4,
                "state_ee": [
                    117,
                    119,
                    146
                ],
                "state_rot": 0,
                "up_down": 0
            },
            {
                "base_action": 0,
                "grasp_drop": 0,
                "mode": 4,
                "state_ee": [
                    117,
                    119,
                    147
                ],
                "state_rot": 0,
                "up_down": 0
            },
            {
                "base_action": 0,
                "grasp_drop": 0,
                "mode": 4,
                "state_ee": [
                    117,
                    119,
                    147
                ],
                "state_rot": 0,
                "up_down": 0
            },
            {
                "base_action": 1,
                "grasp_drop": 0,
                "mode": 1,
                "state_ee": [
                    0,
                    0,
                    0
                ],
                "state_rot": 0,
                "up_down": 0
            },
            {
                "base_action": 1,
                "grasp_drop": 0,
                "mode": 1,
                "state_ee": [
                    0,
                    0,
                    0
                ],
                "state_rot": 0,
                "up_down": 0
            },
            {
                "base_action": 1,
                "grasp_drop": 0,
                "mode": 1,
                "state_ee": [
                    0,
                    0,
                    0
                ],
                "state_rot": 0,
                "up_down": 0
            },
            {
                "base_action": 1,
                "grasp_drop": 0,
                "mode": 1,
                "state_ee": [
                    0,
                    0,
                    0
                ],
                "state_rot": 0,
                "up_down": 0
            },
            {
                "base_action": 0,
                "grasp_drop": 0,
                "mode": 2,
                "state_ee": [
                    0,
                    0,
                    0
                ],
                "state_rot": [
                    213
                ],
                "up_down": 0
            },
            {
                "base_action": 0,
                "grasp_drop": 0,
                "mode": 2,
                "state_ee": [
                    0,
                    0,
                    0
                ],
                "state_rot": [
                    37
                ],
                "up_down": 0
            },
            {
                "base_action": 0,
                "grasp_drop": 0,
                "mode": 2,
                "state_ee": [
                    0,
                    0,
                    0
                ],
                "state_rot": [
                    121
                ],
                "up_down": 0
            },
            {
                "base_action": 1,
                "grasp_drop": 0,
                "mode": 1,
                "state_ee": [
                    0,
                    0,
                    0
                ],
                "state_rot": 0,
                "up_down": 0
            },
            {
                "base_action": 0,
                "grasp_drop": 0,
                "mode": 2,
                "state_ee": [
                    0,
                    0,
                    0
                ],
                "state_rot": [
                    121
                ],
                "up_down": 0
            },
            {
                "base_action": 1,
                "grasp_drop": 0,
                "mode": 1,
                "state_ee": [
                    0,
                    0,
                    0
                ],
                "state_rot": 0,
                "up_down": 0
            },
            {
                "base_action": 0,
                "grasp_drop": 0,
                "mode": 2,
                "state_ee": [
                    0,
                    0,
                    0
                ],
                "state_rot": [
                    121
                ],
                "up_down": 0
            },
            {
                "base_action": 1,
                "grasp_drop": 0,
                "mode": 1,
                "state_ee": [
                    0,
                    0,
                    0
                ],
                "state_rot": 0,
                "up_down": 0
            },
            {
                "base_action": 3,
                "grasp_drop": 0,
                "mode": 1,
                "state_ee": [
                    0,
                    0,
                    0
                ],
                "state_rot": 0,
                "up_down": 0
            },
            {
                "base_action": 1,
                "grasp_drop": 0,
                "mode": 1,
                "state_ee": [
                    0,
                    0,
                    0
                ],
                "state_rot": 0,
                "up_down": 0
            },
            {
                "base_action": 3,
                "grasp_drop": 0,
                "mode": 1,
                "state_ee": [
                    0,
                    0,
                    0
                ],
                "state_rot": 0,
                "up_down": 0
            },
            {
                "base_action": 0,
                "grasp_drop": 0,
                "mode": 2,
                "state_ee": [
                    0,
                    0,
                    0
                ],
                "state_rot": [
                    248
                ],
                "up_down": 0
            },
            {
                "base_action": 1,
                "grasp_drop": 0,
                "mode": 1,
                "state_ee": [
                    0,
                    0,
                    0
                ],
                "state_rot": 0,
                "up_down": 0
            },
            {
                "base_action": 1,
                "grasp_drop": 0,
                "mode": 1,
                "state_ee": [
                    0,
                    0,
                    0
                ],
                "state_rot": 0,
                "up_down": 0
            },
            {
                "base_action": 0,
                "grasp_drop": 0,
                "mode": 2,
                "state_ee": [
                    0,
                    0,
                    0
                ],
                "state_rot": [
                    250
                ],
                "up_down": 0
            },
            {
                "base_action": 3,
                "grasp_drop": 0,
                "mode": 1,
                "state_ee": [
                    0,
                    0,
                    0
                ],
                "state_rot": 0,
                "up_down": 0
            },
            {
                "base_action": 0,
                "grasp_drop": 0,
                "mode": 2,
                "state_ee": [
                    0,
                    0,
                    0
                ],
                "state_rot": [
                    7
                ],
                "up_down": 0
            },
            {
                "base_action": 0,
                "grasp_drop": 0,
                "mode": 2,
                "state_ee": [
                    0,
                    0,
                    0
                ],
                "state_rot": [
                    249
                ],
                "up_down": 0
            },
            {
                "base_action": 2,
                "grasp_drop": 0,
                "mode": 1,
                "state_ee": [
                    0,
                    0,
                    0
                ],
                "state_rot": 0,
                "up_down": 0
            },
            {
                "base_action": 3,
                "grasp_drop": 0,
                "mode": 1,
                "state_ee": [
                    0,
                    0,
                    0
                ],
                "state_rot": 0,
                "up_down": 0
            },
            {
                "base_action": 3,
                "grasp_drop": 0,
                "mode": 1,
                "state_ee": [
                    0,
                    0,
                    0
                ],
                "state_rot": 0,
                "up_down": 0
            },
            {
                "base_action": 1,
                "grasp_drop": 0,
                "mode": 1,
                "state_ee": [
                    0,
                    0,
                    0
                ],
                "state_rot": 0,
                "up_down": 0
            },
            {
                "base_action": 0,
                "grasp_drop": 0,
                "mode": 2,
                "state_ee": [
                    0,
                    0,
                    0
                ],
                "state_rot": [
                    6
                ],
                "up_down": 0
            },
            {
                "base_action": 1,
                "grasp_drop": 0,
                "mode": 1,
                "state_ee": [
                    0,
                    0,
                    0
                ],
                "state_rot": 0,
                "up_down": 0
            },
            {
                "base_action": 1,
                "grasp_drop": 0,
                "mode": 1,
                "state_ee": [
                    0,
                    0,
                    0
                ],
                "state_rot": 0,
                "up_down": 0
            },
            {
                "base_action": 1,
                "grasp_drop": 0,
                "mode": 1,
                "state_ee": [
                    0,
                    0,
                    0
                ],
                "state_rot": 0,
                "up_down": 0
            },
            {
                "base_action": 1,
                "grasp_drop": 0,
                "mode": 1,
                "state_ee": [
                    0,
                    0,
                    0
                ],
                "state_rot": 0,
                "up_down": 0
            },
            {
                "base_action": 1,
                "grasp_drop": 0,
                "mode": 1,
                "state_ee": [
                    0,
                    0,
                    0
                ],
                "state_rot": 0,
                "up_down": 0
            },
            {
                "base_action": 1,
                "grasp_drop": 0,
                "mode": 1,
                "state_ee": [
                    0,
                    0,
                    0
                ],
                "state_rot": 0,
                "up_down": 0
            },
            {
                "base_action": 1,
                "grasp_drop": 0,
                "mode": 1,
                "state_ee": [
                    0,
                    0,
                    0
                ],
                "state_rot": 0,
                "up_down": 0
            },
            {
                "base_action": 0,
                "grasp_drop": 0,
                "mode": 2,
                "state_ee": [
                    0,
                    0,
                    0
                ],
                "state_rot": [
                    7
                ],
                "up_down": 0
            },
            {
                "base_action": 0,
                "grasp_drop": 0,
                "mode": 2,
                "state_ee": [
                    0,
                    0,
                    0
                ],
                "state_rot": [
                    136
                ],
                "up_down": 0
            },
            {
                "base_action": 1,
                "grasp_drop": 0,
                "mode": 1,
                "state_ee": [
                    0,
                    0,
                    0
                ],
                "state_rot": 0,
                "up_down": 0
            },
            {
                "base_action": 0,
                "grasp_drop": 0,
                "mode": 2,
                "state_ee": [
                    0,
                    0,
                    0
                ],
                "state_rot": [
                    127
                ],
                "up_down": 0
            },
            {
                "base_action": 4,
                "grasp_drop": 0,
                "mode": 1,
                "state_ee": [
                    0,
                    0,
                    0
                ],
                "state_rot": 0,
                "up_down": 0
            },
            {
                "base_action": 4,
                "grasp_drop": 0,
                "mode": 1,
                "state_ee": [
                    0,
                    0,
                    0
                ],
                "state_rot": 0,
                "up_down": 0
            },
            {
                "base_action": 4,
                "grasp_drop": 0,
                "mode": 1,
                "state_ee": [
                    0,
                    0,
                    0
                ],
                "state_rot": 0,
                "up_down": 0
            },
            {
                "base_action": 0,
                "grasp_drop": 0,
                "mode": 2,
                "state_ee": [
                    0,
                    0,
                    0
                ],
                "state_rot": [
                    136
                ],
                "up_down": 0
            },
            {
                "base_action": 0,
                "grasp_drop": 0,
                "mode": 2,
                "state_ee": [
                    0,
                    0,
                    0
                ],
                "state_rot": [
                    136
                ],
                "up_down": 0
            },
            {
                "base_action": 1,
                "grasp_drop": 0,
                "mode": 1,
                "state_ee": [
                    0,
                    0,
                    0
                ],
                "state_rot": 0,
                "up_down": 0
            },
            {
                "base_action": 4,
                "grasp_drop": 0,
                "mode": 1,
                "state_ee": [
                    0,
                    0,
                    0
                ],
                "state_rot": 0,
                "up_down": 0
            },
            {
                "base_action": 4,
                "grasp_drop": 0,
                "mode": 1,
                "state_ee": [
                    0,
                    0,
                    0
                ],
                "state_rot": 0,
                "up_down": 0
            },
            {
                "base_action": 4,
                "grasp_drop": 0,
                "mode": 1,
                "state_ee": [
                    0,
                    0,
                    0
                ],
                "state_rot": 0,
                "up_down": 0
            },
            {
                "base_action": 1,
                "grasp_drop": 0,
                "mode": 1,
                "state_ee": [
                    0,
                    0,
                    0
                ],
                "state_rot": 0,
                "up_down": 0
            },
            {
                "base_action": 0,
                "grasp_drop": 0,
                "mode": 2,
                "state_ee": [
                    0,
                    0,
                    0
                ],
                "state_rot": [
                    120
                ],
                "up_down": 0
            },
            {
                "base_action": 0,
                "grasp_drop": 0,
                "mode": 2,
                "state_ee": [
                    0,
                    0,
                    0
                ],
                "state_rot": [
                    145
                ],
                "up_down": 0
            },
            {
                "base_action": 1,
                "grasp_drop": 0,
                "mode": 1,
                "state_ee": [
                    0,
                    0,
                    0
                ],
                "state_rot": 0,
                "up_down": 0
            },
            {
                "base_action": 1,
                "grasp_drop": 0,
                "mode": 1,
                "state_ee": [
                    0,
                    0,
                    0
                ],
                "state_rot": 0,
                "up_down": 0
            },
            {
                "base_action": 1,
                "grasp_drop": 0,
                "mode": 1,
                "state_ee": [
                    0,
                    0,
                    0
                ],
                "state_rot": 0,
                "up_down": 0
            },
            {
                "base_action": 1,
                "grasp_drop": 0,
                "mode": 1,
                "state_ee": [
                    0,
                    0,
                    0
                ],
                "state_rot": 0,
                "up_down": 0
            },
            {
                "base_action": 1,
                "grasp_drop": 0,
                "mode": 1,
                "state_ee": [
                    0,
                    0,
                    0
                ],
                "state_rot": 0,
                "up_down": 0
            },
            {
                "base_action": 1,
                "grasp_drop": 0,
                "mode": 1,
                "state_ee": [
                    0,
                    0,
                    0
                ],
                "state_rot": 0,
                "up_down": 0
            },
            {
                "base_action": 1,
                "grasp_drop": 0,
                "mode": 1,
                "state_ee": [
                    0,
                    0,
                    0
                ],
                "state_rot": 0,
                "up_down": 0
            },
            {
                "base_action": 1,
                "grasp_drop": 0,
                "mode": 1,
                "state_ee": [
                    0,
                    0,
                    0
                ],
                "state_rot": 0,
                "up_down": 0
            },
            {
                "base_action": 1,
                "grasp_drop": 0,
                "mode": 1,
                "state_ee": [
                    0,
                    0,
                    0
                ],
                "state_rot": 0,
                "up_down": 0
            },
            {
                "base_action": 0,
                "grasp_drop": 0,
                "mode": 2,
                "state_ee": [
                    0,
                    0,
                    0
                ],
                "state_rot": [
                    120
                ],
                "up_down": 0
            },
            {
                "base_action": 1,
                "grasp_drop": 0,
                "mode": 1,
                "state_ee": [
                    0,
                    0,
                    0
                ],
                "state_rot": 0,
                "up_down": 0
            },
            {
                "base_action": 1,
                "grasp_drop": 0,
                "mode": 1,
                "state_ee": [
                    0,
                    0,
                    0
                ],
                "state_rot": 0,
                "up_down": 0
            },
            {
                "base_action": 1,
                "grasp_drop": 0,
                "mode": 1,
                "state_ee": [
                    0,
                    0,
                    0
                ],
                "state_rot": 0,
                "up_down": 0
            },
            {
                "base_action": 1,
                "grasp_drop": 0,
                "mode": 1,
                "state_ee": [
                    0,
                    0,
                    0
                ],
                "state_rot": 0,
                "up_down": 0
            },
            {
                "base_action": 1,
                "grasp_drop": 0,
                "mode": 1,
                "state_ee": [
                    0,
                    0,
                    0
                ],
                "state_rot": 0,
                "up_down": 0
            },
            {
                "base_action": 3,
                "grasp_drop": 0,
                "mode": 1,
                "state_ee": [
                    0,
                    0,
                    0
                ],
                "state_rot": 0,
                "up_down": 0
            },
            {
                "base_action": 1,
                "grasp_drop": 0,
                "mode": 1,
                "state_ee": [
                    0,
                    0,
                    0
                ],
                "state_rot": 0,
                "up_down": 0
            },
            {
                "base_action": 0,
                "grasp_drop": 0,
                "mode": 2,
                "state_ee": [
                    0,
                    0,
                    0
                ],
                "state_rot": [
                    121
                ],
                "up_down": 0
            },
            {
                "base_action": 0,
                "grasp_drop": 0,
                "mode": 2,
                "state_ee": [
                    0,
                    0,
                    0
                ],
                "state_rot": [
                    121
                ],
                "up_down": 0
            },
            {
                "base_action": 0,
                "grasp_drop": 0,
                "mode": 2,
                "state_ee": [
                    0,
                    0,
                    0
                ],
                "state_rot": [
                    121
                ],
                "up_down": 0
            },
            {
                "base_action": 0,
                "grasp_drop": 0,
                "mode": 2,
                "state_ee": [
                    0,
                    0,
                    0
                ],
                "state_rot": [
                    148
                ],
                "up_down": 0
            },
            {
                "base_action": 0,
                "grasp_drop": 0,
                "mode": 2,
                "state_ee": [
                    0,
                    0,
                    0
                ],
                "state_rot": [
                    102
                ],
                "up_down": 0
            },
            {
                "base_action": 0,
                "grasp_drop": 0,
                "mode": 3,
                "state_ee": [
                    0,
                    0,
                    0
                ],
                "state_rot": 0,
                "up_down": 0
            },
            {
                "base_action": 0,
                "grasp_drop": 0,
                "mode": 3,
                "state_ee": [
                    0,
                    0,
                    0
                ],
                "state_rot": 0,
                "up_down": 0
            },
            {
                "base_action": 0,
                "grasp_drop": 0,
                "mode": 4,
                "state_ee": [
                    117,
                    119,
                    145
                ],
                "state_rot": 0,
                "up_down": 0
            },
            {
                "base_action": 0,
                "grasp_drop": 0,
                "mode": 4,
                "state_ee": [
                    117,
                    119,
                    145
                ],
                "state_rot": 0,
                "up_down": 0
            },
            {
                "base_action": 0,
                "grasp_drop": 0,
                "mode": 4,
                "state_ee": [
                    117,
                    119,
                    144
                ],
                "state_rot": 0,
                "up_down": 0
            },
            {
                "base_action": 0,
                "grasp_drop": 0,
                "mode": 4,
                "state_ee": [
                    117,
                    119,
                    143
                ],
                "state_rot": 0,
                "up_down": 0
            },
            {
                "base_action": 0,
                "grasp_drop": 0,
                "mode": 4,
                "state_ee": [
                    117,
                    119,
                    142
                ],
                "state_rot": 0,
                "up_down": 0
            },
            {
                "base_action": 0,
                "grasp_drop": 0,
                "mode": 4,
                "state_ee": [
                    117,
                    119,
                    142
                ],
                "state_rot": 0,
                "up_down": 0
            },
            {
                "base_action": 0,
                "grasp_drop": 0,
                "mode": 3,
                "state_ee": [
                    0,
                    0,
                    0
                ],
                "state_rot": 0,
                "up_down": 0
            },
            {
                "base_action": 0,
                "grasp_drop": 0,
                "mode": 2,
                "state_ee": [
                    0,
                    0,
                    0
                ],
                "state_rot": [
                    156
                ],
                "up_down": 0
            },
            {
                "base_action": 0,
                "grasp_drop": 0,
                "mode": 3,
                "state_ee": [
                    0,
                    0,
                    0
                ],
                "state_rot": 0,
                "up_down": 0
            },
            {
                "base_action": 0,
                "grasp_drop": 0,
                "mode": 4,
                "state_ee": [
                    117,
                    119,
                    142
                ],
                "state_rot": 0,
                "up_down": 0
            },
            {
                "base_action": 0,
                "grasp_drop": 0,
                "mode": 4,
                "state_ee": [
                    117,
                    119,
                    144
                ],
                "state_rot": 0,
                "up_down": 0
            },
            {
                "base_action": 0,
                "grasp_drop": 0,
                "mode": 4,
                "state_ee": [
                    117,
                    119,
                    146
                ],
                "state_rot": 0,
                "up_down": 0
            },
            {
                "base_action": 0,
                "grasp_drop": 0,
                "mode": 4,
                "state_ee": [
                    117,
                    119,
                    147
                ],
                "state_rot": 0,
                "up_down": 0
            },
            {
                "base_action": 0,
                "grasp_drop": 0,
                "mode": 4,
                "state_ee": [
                    117,
                    119,
                    148
                ],
                "state_rot": 0,
                "up_down": 0
            },
            {
                "base_action": 0,
                "grasp_drop": 0,
                "mode": 4,
                "state_ee": [
                    117,
                    119,
                    148
                ],
                "state_rot": 0,
                "up_down": 0
            },
            {
                "base_action": 0,
                "grasp_drop": 0,
                "mode": 4,
                "state_ee": [
                    118,
                    119,
                    149
                ],
                "state_rot": 0,
                "up_down": 0
            },
            {
                "base_action": 0,
                "grasp_drop": 0,
                "mode": 4,
                "state_ee": [
                    118,
                    119,
                    150
                ],
                "state_rot": 0,
                "up_down": 0
            },
            {
                "base_action": 0,
                "grasp_drop": 0,
                "mode": 4,
                "state_ee": [
                    118,
                    119,
                    150
                ],
                "state_rot": 0,
                "up_down": 0
            },
            {
                "base_action": 0,
                "grasp_drop": 0,
                "mode": 0,
                "state_ee": [
                    0,
                    0,
                    0
                ],
                "state_rot": [
                    0
                ],
                "up_down": 0
            }
        ],
        "lang_goal": [
            3,
            4,
            5,
            64,
            15,
            16,
            17,
            5,
            238,
            19,
            73,
            3,
            4,
            5,
            27,
            6,
            15,
            37,
            5,
            238,
            32,
            4,
            5,
            51,
            19,
            2
        ]
    },
    "root": "data/feats_discrete_relative_task/data_15:30:35",
    "scene": "FloorPlan_Train8_1",
    "split": "train"
}