{
    "ann": {
        "goal": [
            " go ",
            " toward ",
            " the ",
            " tan ",
            " chair ",
            " with ",
            " the ",
            " books ",
            ", ",
            " grab ",
            " the ",
            " top ",
            " white ",
            " book ",
            ". ",
            " then ",
            " go ",
            " back ",
            " into ",
            " the ",
            " living ",
            " room ",
            " and ",
            " put ",
            " it ",
            " on ",
            " top ",
            " of ",
            " the ",
            " wooden ",
            " dresser ",
            " beside ",
            " the ",
            " glass ",
            " vase ",
            ". ",
            "<<goal>>"
        ],
        "task_desc": "Go toward the tan chair with the books, grab the top white book. Then go back into the living room and put it on top of the wooden dresser beside the glass vase."
    },
    "num": {
        "action_low": [
            {
                "base_action": 0,
                "grasp_drop": 0,
                "mode": 5,
                "state_ee": [
                    0,
                    0,
                    0
                ],
                "state_rot": 0,
                "up_down": 2
            },
            {
                "base_action": 0,
                "grasp_drop": 0,
                "mode": 2,
                "state_ee": [
                    0,
                    0,
                    0
                ],
                "state_rot": [
                    228
                ],
                "up_down": 0
            },
            {
                "base_action": 0,
                "grasp_drop": 0,
                "mode": 3,
                "state_ee": [
                    86,
                    138,
                    224
                ],
                "state_rot": 0,
                "up_down": 0
            },
            {
                "base_action": 0,
                "grasp_drop": 0,
                "mode": 3,
                "state_ee": [
                    117,
                    116,
                    146
                ],
                "state_rot": 0,
                "up_down": 0
            },
            {
                "base_action": 0,
                "grasp_drop": 0,
                "mode": 3,
                "state_ee": [
                    117,
                    116,
                    146
                ],
                "state_rot": 0,
                "up_down": 0
            },
            {
                "base_action": 0,
                "grasp_drop": 0,
                "mode": 3,
                "state_ee": [
                    117,
                    116,
                    146
                ],
                "state_rot": 0,
                "up_down": 0
            },
            {
                "base_action": 2,
                "grasp_drop": 0,
                "mode": 1,
                "state_ee": [
                    0,
                    0,
                    0
                ],
                "state_rot": 0,
                "up_down": 0
            },
            {
                "base_action": 0,
                "grasp_drop": 1,
                "mode": 4,
                "state_ee": [
                    0,
                    0,
                    0
                ],
                "state_rot": 0,
                "up_down": 0
            },
            {
                "base_action": 0,
                "grasp_drop": 0,
                "mode": 3,
                "state_ee": [
                    117,
                    121,
                    146
                ],
                "state_rot": 0,
                "up_down": 0
            },
            {
                "base_action": 0,
                "grasp_drop": 0,
                "mode": 3,
                "state_ee": [
                    117,
                    121,
                    146
                ],
                "state_rot": 0,
                "up_down": 0
            },
            {
                "base_action": 0,
                "grasp_drop": 0,
                "mode": 3,
                "state_ee": [
                    117,
                    121,
                    146
                ],
                "state_rot": 0,
                "up_down": 0
            },
            {
                "base_action": 0,
                "grasp_drop": 0,
                "mode": 3,
                "state_ee": [
                    117,
                    121,
                    146
                ],
                "state_rot": 0,
                "up_down": 0
            },
            {
                "base_action": 0,
                "grasp_drop": 0,
                "mode": 2,
                "state_ee": [
                    0,
                    0,
                    0
                ],
                "state_rot": [
                    118
                ],
                "up_down": 0
            },
            {
                "base_action": 0,
                "grasp_drop": 0,
                "mode": 3,
                "state_ee": [
                    91,
                    143,
                    226
                ],
                "state_rot": 0,
                "up_down": 0
            },
            {
                "base_action": 0,
                "grasp_drop": 0,
                "mode": 3,
                "state_ee": [
                    117,
                    121,
                    146
                ],
                "state_rot": 0,
                "up_down": 0
            },
            {
                "base_action": 3,
                "grasp_drop": 0,
                "mode": 1,
                "state_ee": [
                    0,
                    0,
                    0
                ],
                "state_rot": 0,
                "up_down": 0
            },
            {
                "base_action": 2,
                "grasp_drop": 0,
                "mode": 1,
                "state_ee": [
                    0,
                    0,
                    0
                ],
                "state_rot": 0,
                "up_down": 0
            },
            {
                "base_action": 3,
                "grasp_drop": 0,
                "mode": 1,
                "state_ee": [
                    0,
                    0,
                    0
                ],
                "state_rot": 0,
                "up_down": 0
            },
            {
                "base_action": 0,
                "grasp_drop": 0,
                "mode": 2,
                "state_ee": [
                    0,
                    0,
                    0
                ],
                "state_rot": [
                    125
                ],
                "up_down": 0
            },
            {
                "base_action": 3,
                "grasp_drop": 0,
                "mode": 1,
                "state_ee": [
                    0,
                    0,
                    0
                ],
                "state_rot": 0,
                "up_down": 0
            },
            {
                "base_action": 2,
                "grasp_drop": 0,
                "mode": 1,
                "state_ee": [
                    0,
                    0,
                    0
                ],
                "state_rot": 0,
                "up_down": 0
            },
            {
                "base_action": 0,
                "grasp_drop": 0,
                "mode": 3,
                "state_ee": [
                    118,
                    119,
                    146
                ],
                "state_rot": 0,
                "up_down": 0
            },
            {
                "base_action": 0,
                "grasp_drop": 0,
                "mode": 3,
                "state_ee": [
                    118,
                    119,
                    146
                ],
                "state_rot": 0,
                "up_down": 0
            },
            {
                "base_action": 1,
                "grasp_drop": 0,
                "mode": 1,
                "state_ee": [
                    0,
                    0,
                    0
                ],
                "state_rot": 0,
                "up_down": 0
            },
            {
                "base_action": 0,
                "grasp_drop": 0,
                "mode": 3,
                "state_ee": [
                    98,
                    146,
                    230
                ],
                "state_rot": 0,
                "up_down": 0
            },
            {
                "base_action": 0,
                "grasp_drop": 0,
                "mode": 3,
                "state_ee": [
                    119,
                    119,
                    146
                ],
                "state_rot": 0,
                "up_down": 0
            },
            {
                "base_action": 3,
                "grasp_drop": 0,
                "mode": 1,
                "state_ee": [
                    0,
                    0,
                    0
                ],
                "state_rot": 0,
                "up_down": 0
            },
            {
                "base_action": 2,
                "grasp_drop": 0,
                "mode": 1,
                "state_ee": [
                    0,
                    0,
                    0
                ],
                "state_rot": 0,
                "up_down": 0
            },
            {
                "base_action": 2,
                "grasp_drop": 0,
                "mode": 1,
                "state_ee": [
                    0,
                    0,
                    0
                ],
                "state_rot": 0,
                "up_down": 0
            },
            {
                "base_action": 2,
                "grasp_drop": 0,
                "mode": 1,
                "state_ee": [
                    0,
                    0,
                    0
                ],
                "state_rot": 0,
                "up_down": 0
            },
            {
                "base_action": 0,
                "grasp_drop": 0,
                "mode": 2,
                "state_ee": [
                    0,
                    0,
                    0
                ],
                "state_rot": [
                    121
                ],
                "up_down": 0
            },
            {
                "base_action": 0,
                "grasp_drop": 0,
                "mode": 2,
                "state_ee": [
                    0,
                    0,
                    0
                ],
                "state_rot": [
                    121
                ],
                "up_down": 0
            },
            {
                "base_action": 2,
                "grasp_drop": 0,
                "mode": 1,
                "state_ee": [
                    0,
                    0,
                    0
                ],
                "state_rot": 0,
                "up_down": 0
            },
            {
                "base_action": 2,
                "grasp_drop": 0,
                "mode": 1,
                "state_ee": [
                    0,
                    0,
                    0
                ],
                "state_rot": 0,
                "up_down": 0
            },
            {
                "base_action": 1,
                "grasp_drop": 0,
                "mode": 1,
                "state_ee": [
                    0,
                    0,
                    0
                ],
                "state_rot": 0,
                "up_down": 0
            },
            {
                "base_action": 2,
                "grasp_drop": 0,
                "mode": 1,
                "state_ee": [
                    0,
                    0,
                    0
                ],
                "state_rot": 0,
                "up_down": 0
            },
            {
                "base_action": 2,
                "grasp_drop": 0,
                "mode": 1,
                "state_ee": [
                    0,
                    0,
                    0
                ],
                "state_rot": 0,
                "up_down": 0
            },
            {
                "base_action": 4,
                "grasp_drop": 0,
                "mode": 1,
                "state_ee": [
                    0,
                    0,
                    0
                ],
                "state_rot": 0,
                "up_down": 0
            },
            {
                "base_action": 2,
                "grasp_drop": 0,
                "mode": 1,
                "state_ee": [
                    0,
                    0,
                    0
                ],
                "state_rot": 0,
                "up_down": 0
            },
            {
                "base_action": 2,
                "grasp_drop": 0,
                "mode": 1,
                "state_ee": [
                    0,
                    0,
                    0
                ],
                "state_rot": 0,
                "up_down": 0
            },
            {
                "base_action": 4,
                "grasp_drop": 0,
                "mode": 1,
                "state_ee": [
                    0,
                    0,
                    0
                ],
                "state_rot": 0,
                "up_down": 0
            },
            {
                "base_action": 2,
                "grasp_drop": 0,
                "mode": 1,
                "state_ee": [
                    0,
                    0,
                    0
                ],
                "state_rot": 0,
                "up_down": 0
            },
            {
                "base_action": 2,
                "grasp_drop": 0,
                "mode": 1,
                "state_ee": [
                    0,
                    0,
                    0
                ],
                "state_rot": 0,
                "up_down": 0
            },
            {
                "base_action": 0,
                "grasp_drop": 0,
                "mode": 2,
                "state_ee": [
                    0,
                    0,
                    0
                ],
                "state_rot": [
                    129
                ],
                "up_down": 0
            },
            {
                "base_action": 4,
                "grasp_drop": 0,
                "mode": 1,
                "state_ee": [
                    0,
                    0,
                    0
                ],
                "state_rot": 0,
                "up_down": 0
            },
            {
                "base_action": 1,
                "grasp_drop": 0,
                "mode": 1,
                "state_ee": [
                    0,
                    0,
                    0
                ],
                "state_rot": 0,
                "up_down": 0
            },
            {
                "base_action": 2,
                "grasp_drop": 0,
                "mode": 1,
                "state_ee": [
                    0,
                    0,
                    0
                ],
                "state_rot": 0,
                "up_down": 0
            },
            {
                "base_action": 2,
                "grasp_drop": 0,
                "mode": 1,
                "state_ee": [
                    0,
                    0,
                    0
                ],
                "state_rot": 0,
                "up_down": 0
            },
            {
                "base_action": 4,
                "grasp_drop": 0,
                "mode": 1,
                "state_ee": [
                    0,
                    0,
                    0
                ],
                "state_rot": 0,
                "up_down": 0
            },
            {
                "base_action": 2,
                "grasp_drop": 0,
                "mode": 1,
                "state_ee": [
                    0,
                    0,
                    0
                ],
                "state_rot": 0,
                "up_down": 0
            },
            {
                "base_action": 2,
                "grasp_drop": 0,
                "mode": 1,
                "state_ee": [
                    0,
                    0,
                    0
                ],
                "state_rot": 0,
                "up_down": 0
            },
            {
                "base_action": 4,
                "grasp_drop": 0,
                "mode": 1,
                "state_ee": [
                    0,
                    0,
                    0
                ],
                "state_rot": 0,
                "up_down": 0
            },
            {
                "base_action": 2,
                "grasp_drop": 0,
                "mode": 1,
                "state_ee": [
                    0,
                    0,
                    0
                ],
                "state_rot": 0,
                "up_down": 0
            },
            {
                "base_action": 2,
                "grasp_drop": 0,
                "mode": 1,
                "state_ee": [
                    0,
                    0,
                    0
                ],
                "state_rot": 0,
                "up_down": 0
            },
            {
                "base_action": 4,
                "grasp_drop": 0,
                "mode": 1,
                "state_ee": [
                    0,
                    0,
                    0
                ],
                "state_rot": 0,
                "up_down": 0
            },
            {
                "base_action": 2,
                "grasp_drop": 0,
                "mode": 1,
                "state_ee": [
                    0,
                    0,
                    0
                ],
                "state_rot": 0,
                "up_down": 0
            },
            {
                "base_action": 0,
                "grasp_drop": 0,
                "mode": 2,
                "state_ee": [
                    0,
                    0,
                    0
                ],
                "state_rot": [
                    143
                ],
                "up_down": 0
            },
            {
                "base_action": 2,
                "grasp_drop": 0,
                "mode": 1,
                "state_ee": [
                    0,
                    0,
                    0
                ],
                "state_rot": 0,
                "up_down": 0
            },
            {
                "base_action": 4,
                "grasp_drop": 0,
                "mode": 1,
                "state_ee": [
                    0,
                    0,
                    0
                ],
                "state_rot": 0,
                "up_down": 0
            },
            {
                "base_action": 4,
                "grasp_drop": 0,
                "mode": 1,
                "state_ee": [
                    0,
                    0,
                    0
                ],
                "state_rot": 0,
                "up_down": 0
            },
            {
                "base_action": 2,
                "grasp_drop": 0,
                "mode": 1,
                "state_ee": [
                    0,
                    0,
                    0
                ],
                "state_rot": 0,
                "up_down": 0
            },
            {
                "base_action": 2,
                "grasp_drop": 0,
                "mode": 1,
                "state_ee": [
                    0,
                    0,
                    0
                ],
                "state_rot": 0,
                "up_down": 0
            },
            {
                "base_action": 2,
                "grasp_drop": 0,
                "mode": 1,
                "state_ee": [
                    0,
                    0,
                    0
                ],
                "state_rot": 0,
                "up_down": 0
            },
            {
                "base_action": 4,
                "grasp_drop": 0,
                "mode": 1,
                "state_ee": [
                    0,
                    0,
                    0
                ],
                "state_rot": 0,
                "up_down": 0
            },
            {
                "base_action": 0,
                "grasp_drop": 0,
                "mode": 2,
                "state_ee": [
                    0,
                    0,
                    0
                ],
                "state_rot": [
                    121
                ],
                "up_down": 0
            },
            {
                "base_action": 2,
                "grasp_drop": 0,
                "mode": 1,
                "state_ee": [
                    0,
                    0,
                    0
                ],
                "state_rot": 0,
                "up_down": 0
            },
            {
                "base_action": 2,
                "grasp_drop": 0,
                "mode": 1,
                "state_ee": [
                    0,
                    0,
                    0
                ],
                "state_rot": 0,
                "up_down": 0
            },
            {
                "base_action": 1,
                "grasp_drop": 0,
                "mode": 1,
                "state_ee": [
                    0,
                    0,
                    0
                ],
                "state_rot": 0,
                "up_down": 0
            },
            {
                "base_action": 4,
                "grasp_drop": 0,
                "mode": 1,
                "state_ee": [
                    0,
                    0,
                    0
                ],
                "state_rot": 0,
                "up_down": 0
            },
            {
                "base_action": 2,
                "grasp_drop": 0,
                "mode": 1,
                "state_ee": [
                    0,
                    0,
                    0
                ],
                "state_rot": 0,
                "up_down": 0
            },
            {
                "base_action": 4,
                "grasp_drop": 0,
                "mode": 1,
                "state_ee": [
                    0,
                    0,
                    0
                ],
                "state_rot": 0,
                "up_down": 0
            },
            {
                "base_action": 2,
                "grasp_drop": 0,
                "mode": 1,
                "state_ee": [
                    0,
                    0,
                    0
                ],
                "state_rot": 0,
                "up_down": 0
            },
            {
                "base_action": 0,
                "grasp_drop": 0,
                "mode": 2,
                "state_ee": [
                    0,
                    0,
                    0
                ],
                "state_rot": [
                    121
                ],
                "up_down": 0
            },
            {
                "base_action": 0,
                "grasp_drop": 0,
                "mode": 2,
                "state_ee": [
                    0,
                    0,
                    0
                ],
                "state_rot": [
                    121
                ],
                "up_down": 0
            },
            {
                "base_action": 1,
                "grasp_drop": 0,
                "mode": 1,
                "state_ee": [
                    0,
                    0,
                    0
                ],
                "state_rot": 0,
                "up_down": 0
            },
            {
                "base_action": 1,
                "grasp_drop": 0,
                "mode": 1,
                "state_ee": [
                    0,
                    0,
                    0
                ],
                "state_rot": 0,
                "up_down": 0
            },
            {
                "base_action": 3,
                "grasp_drop": 0,
                "mode": 1,
                "state_ee": [
                    0,
                    0,
                    0
                ],
                "state_rot": 0,
                "up_down": 0
            },
            {
                "base_action": 3,
                "grasp_drop": 0,
                "mode": 1,
                "state_ee": [
                    0,
                    0,
                    0
                ],
                "state_rot": 0,
                "up_down": 0
            },
            {
                "base_action": 1,
                "grasp_drop": 0,
                "mode": 1,
                "state_ee": [
                    0,
                    0,
                    0
                ],
                "state_rot": 0,
                "up_down": 0
            },
            {
                "base_action": 3,
                "grasp_drop": 0,
                "mode": 1,
                "state_ee": [
                    0,
                    0,
                    0
                ],
                "state_rot": 0,
                "up_down": 0
            },
            {
                "base_action": 1,
                "grasp_drop": 0,
                "mode": 1,
                "state_ee": [
                    0,
                    0,
                    0
                ],
                "state_rot": 0,
                "up_down": 0
            },
            {
                "base_action": 1,
                "grasp_drop": 0,
                "mode": 1,
                "state_ee": [
                    0,
                    0,
                    0
                ],
                "state_rot": 0,
                "up_down": 0
            },
            {
                "base_action": 1,
                "grasp_drop": 0,
                "mode": 1,
                "state_ee": [
                    0,
                    0,
                    0
                ],
                "state_rot": 0,
                "up_down": 0
            },
            {
                "base_action": 0,
                "grasp_drop": 0,
                "mode": 2,
                "state_ee": [
                    0,
                    0,
                    0
                ],
                "state_rot": [
                    121
                ],
                "up_down": 0
            },
            {
                "base_action": 0,
                "grasp_drop": 0,
                "mode": 2,
                "state_ee": [
                    0,
                    0,
                    0
                ],
                "state_rot": [
                    121
                ],
                "up_down": 0
            },
            {
                "base_action": 0,
                "grasp_drop": 0,
                "mode": 2,
                "state_ee": [
                    0,
                    0,
                    0
                ],
                "state_rot": [
                    121
                ],
                "up_down": 0
            },
            {
                "base_action": 2,
                "grasp_drop": 0,
                "mode": 1,
                "state_ee": [
                    0,
                    0,
                    0
                ],
                "state_rot": 0,
                "up_down": 0
            },
            {
                "base_action": 0,
                "grasp_drop": 0,
                "mode": 3,
                "state_ee": [
                    117,
                    121,
                    146
                ],
                "state_rot": 0,
                "up_down": 0
            },
            {
                "base_action": 0,
                "grasp_drop": 0,
                "mode": 3,
                "state_ee": [
                    117,
                    121,
                    146
                ],
                "state_rot": 0,
                "up_down": 0
            },
            {
                "base_action": 1,
                "grasp_drop": 0,
                "mode": 1,
                "state_ee": [
                    0,
                    0,
                    0
                ],
                "state_rot": 0,
                "up_down": 0
            },
            {
                "base_action": 0,
                "grasp_drop": 0,
                "mode": 3,
                "state_ee": [
                    178,
                    154,
                    194
                ],
                "state_rot": 0,
                "up_down": 0
            },
            {
                "base_action": 0,
                "grasp_drop": 0,
                "mode": 2,
                "state_ee": [
                    0,
                    0,
                    0
                ],
                "state_rot": [
                    121
                ],
                "up_down": 0
            },
            {
                "base_action": 1,
                "grasp_drop": 0,
                "mode": 1,
                "state_ee": [
                    0,
                    0,
                    0
                ],
                "state_rot": 0,
                "up_down": 0
            },
            {
                "base_action": 0,
                "grasp_drop": 0,
                "mode": 3,
                "state_ee": [
                    117,
                    121,
                    146
                ],
                "state_rot": 0,
                "up_down": 0
            },
            {
                "base_action": 0,
                "grasp_drop": 0,
                "mode": 3,
                "state_ee": [
                    117,
                    121,
                    146
                ],
                "state_rot": 0,
                "up_down": 0
            },
            {
                "base_action": 0,
                "grasp_drop": 0,
                "mode": 3,
                "state_ee": [
                    117,
                    121,
                    146
                ],
                "state_rot": 0,
                "up_down": 0
            },
            {
                "base_action": 0,
                "grasp_drop": 0,
                "mode": 3,
                "state_ee": [
                    117,
                    121,
                    146
                ],
                "state_rot": 0,
                "up_down": 0
            },
            {
                "base_action": 0,
                "grasp_drop": 0,
                "mode": 3,
                "state_ee": [
                    117,
                    121,
                    146
                ],
                "state_rot": 0,
                "up_down": 0
            },
            {
                "base_action": 0,
                "grasp_drop": 0,
                "mode": 3,
                "state_ee": [
                    117,
                    121,
                    146
                ],
                "state_rot": 0,
                "up_down": 0
            },
            {
                "base_action": 0,
                "grasp_drop": 0,
                "mode": 3,
                "state_ee": [
                    117,
                    121,
                    146
                ],
                "state_rot": 0,
                "up_down": 0
            },
            {
                "base_action": 1,
                "grasp_drop": 0,
                "mode": 1,
                "state_ee": [
                    0,
                    0,
                    0
                ],
                "state_rot": 0,
                "up_down": 0
            },
            {
                "base_action": 0,
                "grasp_drop": 0,
                "mode": 3,
                "state_ee": [
                    185,
                    175,
                    192
                ],
                "state_rot": 0,
                "up_down": 0
            },
            {
                "base_action": 0,
                "grasp_drop": 0,
                "mode": 3,
                "state_ee": [
                    117,
                    121,
                    146
                ],
                "state_rot": 0,
                "up_down": 0
            },
            {
                "base_action": 0,
                "grasp_drop": 0,
                "mode": 3,
                "state_ee": [
                    117,
                    121,
                    146
                ],
                "state_rot": 0,
                "up_down": 0
            },
            {
                "base_action": 0,
                "grasp_drop": 0,
                "mode": 3,
                "state_ee": [
                    117,
                    121,
                    146
                ],
                "state_rot": 0,
                "up_down": 0
            },
            {
                "base_action": 0,
                "grasp_drop": 0,
                "mode": 3,
                "state_ee": [
                    117,
                    121,
                    146
                ],
                "state_rot": 0,
                "up_down": 0
            },
            {
                "base_action": 0,
                "grasp_drop": 0,
                "mode": 2,
                "state_ee": [
                    0,
                    0,
                    0
                ],
                "state_rot": [
                    121
                ],
                "up_down": 0
            },
            {
                "base_action": 1,
                "grasp_drop": 0,
                "mode": 1,
                "state_ee": [
                    0,
                    0,
                    0
                ],
                "state_rot": 0,
                "up_down": 0
            },
            {
                "base_action": 3,
                "grasp_drop": 0,
                "mode": 1,
                "state_ee": [
                    0,
                    0,
                    0
                ],
                "state_rot": 0,
                "up_down": 0
            },
            {
                "base_action": 1,
                "grasp_drop": 0,
                "mode": 1,
                "state_ee": [
                    0,
                    0,
                    0
                ],
                "state_rot": 0,
                "up_down": 0
            },
            {
                "base_action": 0,
                "grasp_drop": 0,
                "mode": 3,
                "state_ee": [
                    116,
                    119,
                    146
                ],
                "state_rot": 0,
                "up_down": 0
            },
            {
                "base_action": 2,
                "grasp_drop": 0,
                "mode": 1,
                "state_ee": [
                    0,
                    0,
                    0
                ],
                "state_rot": 0,
                "up_down": 0
            },
            {
                "base_action": 1,
                "grasp_drop": 0,
                "mode": 1,
                "state_ee": [
                    0,
                    0,
                    0
                ],
                "state_rot": 0,
                "up_down": 0
            },
            {
                "base_action": 0,
                "grasp_drop": 0,
                "mode": 3,
                "state_ee": [
                    194,
                    186,
                    188
                ],
                "state_rot": 0,
                "up_down": 0
            },
            {
                "base_action": 0,
                "grasp_drop": 0,
                "mode": 3,
                "state_ee": [
                    117,
                    119,
                    146
                ],
                "state_rot": 0,
                "up_down": 0
            },
            {
                "base_action": 0,
                "grasp_drop": 0,
                "mode": 3,
                "state_ee": [
                    118,
                    119,
                    146
                ],
                "state_rot": 0,
                "up_down": 0
            },
            {
                "base_action": 0,
                "grasp_drop": 0,
                "mode": 3,
                "state_ee": [
                    118,
                    119,
                    146
                ],
                "state_rot": 0,
                "up_down": 0
            },
            {
                "base_action": 0,
                "grasp_drop": 0,
                "mode": 3,
                "state_ee": [
                    118,
                    119,
                    146
                ],
                "state_rot": 0,
                "up_down": 0
            },
            {
                "base_action": 0,
                "grasp_drop": 0,
                "mode": 3,
                "state_ee": [
                    119,
                    119,
                    147
                ],
                "state_rot": 0,
                "up_down": 0
            },
            {
                "base_action": 0,
                "grasp_drop": 2,
                "mode": 4,
                "state_ee": [
                    0,
                    0,
                    0
                ],
                "state_rot": 0,
                "up_down": 0
            },
            {
                "base_action": 2,
                "grasp_drop": 0,
                "mode": 1,
                "state_ee": [
                    0,
                    0,
                    0
                ],
                "state_rot": 0,
                "up_down": 0
            },
            {
                "base_action": 2,
                "grasp_drop": 0,
                "mode": 1,
                "state_ee": [
                    0,
                    0,
                    0
                ],
                "state_rot": 0,
                "up_down": 0
            },
            {
                "base_action": 2,
                "grasp_drop": 0,
                "mode": 1,
                "state_ee": [
                    0,
                    0,
                    0
                ],
                "state_rot": 0,
                "up_down": 0
            },
            {
                "base_action": 1,
                "grasp_drop": 0,
                "mode": 1,
                "state_ee": [
                    0,
                    0,
                    0
                ],
                "state_rot": 0,
                "up_down": 0
            },
            {
                "base_action": 2,
                "grasp_drop": 0,
                "mode": 1,
                "state_ee": [
                    0,
                    0,
                    0
                ],
                "state_rot": 0,
                "up_down": 0
            },
            {
                "base_action": 1,
                "grasp_drop": 0,
                "mode": 1,
                "state_ee": [
                    0,
                    0,
                    0
                ],
                "state_rot": 0,
                "up_down": 0
            },
            {
                "base_action": 1,
                "grasp_drop": 0,
                "mode": 1,
                "state_ee": [
                    0,
                    0,
                    0
                ],
                "state_rot": 0,
                "up_down": 0
            },
            {
                "base_action": 1,
                "grasp_drop": 0,
                "mode": 1,
                "state_ee": [
                    0,
                    0,
                    0
                ],
                "state_rot": 0,
                "up_down": 0
            },
            {
                "base_action": 0,
                "grasp_drop": 0,
                "mode": 2,
                "state_ee": [
                    0,
                    0,
                    0
                ],
                "state_rot": [
                    136
                ],
                "up_down": 0
            },
            {
                "base_action": 0,
                "grasp_drop": 0,
                "mode": 2,
                "state_ee": [
                    0,
                    0,
                    0
                ],
                "state_rot": [
                    136
                ],
                "up_down": 0
            },
            {
                "base_action": 0,
                "grasp_drop": 0,
                "mode": 2,
                "state_ee": [
                    0,
                    0,
                    0
                ],
                "state_rot": [
                    136
                ],
                "up_down": 0
            },
            {
                "base_action": 0,
                "grasp_drop": 0,
                "mode": 2,
                "state_ee": [
                    0,
                    0,
                    0
                ],
                "state_rot": [
                    131
                ],
                "up_down": 0
            },
            {
                "base_action": 1,
                "grasp_drop": 0,
                "mode": 1,
                "state_ee": [
                    0,
                    0,
                    0
                ],
                "state_rot": 0,
                "up_down": 0
            },
            {
                "base_action": 1,
                "grasp_drop": 0,
                "mode": 1,
                "state_ee": [
                    0,
                    0,
                    0
                ],
                "state_rot": 0,
                "up_down": 0
            },
            {
                "base_action": 1,
                "grasp_drop": 0,
                "mode": 1,
                "state_ee": [
                    0,
                    0,
                    0
                ],
                "state_rot": 0,
                "up_down": 0
            },
            {
                "base_action": 2,
                "grasp_drop": 0,
                "mode": 1,
                "state_ee": [
                    0,
                    0,
                    0
                ],
                "state_rot": 0,
                "up_down": 0
            },
            {
                "base_action": 1,
                "grasp_drop": 0,
                "mode": 1,
                "state_ee": [
                    0,
                    0,
                    0
                ],
                "state_rot": 0,
                "up_down": 0
            },
            {
                "base_action": 1,
                "grasp_drop": 0,
                "mode": 1,
                "state_ee": [
                    0,
                    0,
                    0
                ],
                "state_rot": 0,
                "up_down": 0
            },
            {
                "base_action": 1,
                "grasp_drop": 0,
                "mode": 1,
                "state_ee": [
                    0,
                    0,
                    0
                ],
                "state_rot": 0,
                "up_down": 0
            },
            {
                "base_action": 1,
                "grasp_drop": 0,
                "mode": 1,
                "state_ee": [
                    0,
                    0,
                    0
                ],
                "state_rot": 0,
                "up_down": 0
            },
            {
                "base_action": 1,
                "grasp_drop": 0,
                "mode": 1,
                "state_ee": [
                    0,
                    0,
                    0
                ],
                "state_rot": 0,
                "up_down": 0
            },
            {
                "base_action": 3,
                "grasp_drop": 0,
                "mode": 1,
                "state_ee": [
                    0,
                    0,
                    0
                ],
                "state_rot": 0,
                "up_down": 0
            },
            {
                "base_action": 3,
                "grasp_drop": 0,
                "mode": 1,
                "state_ee": [
                    0,
                    0,
                    0
                ],
                "state_rot": 0,
                "up_down": 0
            },
            {
                "base_action": 1,
                "grasp_drop": 0,
                "mode": 1,
                "state_ee": [
                    0,
                    0,
                    0
                ],
                "state_rot": 0,
                "up_down": 0
            },
            {
                "base_action": 1,
                "grasp_drop": 0,
                "mode": 1,
                "state_ee": [
                    0,
                    0,
                    0
                ],
                "state_rot": 0,
                "up_down": 0
            },
            {
                "base_action": 3,
                "grasp_drop": 0,
                "mode": 1,
                "state_ee": [
                    0,
                    0,
                    0
                ],
                "state_rot": 0,
                "up_down": 0
            },
            {
                "base_action": 0,
                "grasp_drop": 0,
                "mode": 2,
                "state_ee": [
                    0,
                    0,
                    0
                ],
                "state_rot": [
                    126
                ],
                "up_down": 0
            },
            {
                "base_action": 0,
                "grasp_drop": 0,
                "mode": 2,
                "state_ee": [
                    0,
                    0,
                    0
                ],
                "state_rot": [
                    124
                ],
                "up_down": 0
            },
            {
                "base_action": 1,
                "grasp_drop": 0,
                "mode": 1,
                "state_ee": [
                    0,
                    0,
                    0
                ],
                "state_rot": 0,
                "up_down": 0
            },
            {
                "base_action": 0,
                "grasp_drop": 0,
                "mode": 2,
                "state_ee": [
                    0,
                    0,
                    0
                ],
                "state_rot": [
                    121
                ],
                "up_down": 0
            },
            {
                "base_action": 3,
                "grasp_drop": 0,
                "mode": 1,
                "state_ee": [
                    0,
                    0,
                    0
                ],
                "state_rot": 0,
                "up_down": 0
            },
            {
                "base_action": 0,
                "grasp_drop": 0,
                "mode": 3,
                "state_ee": [
                    117,
                    124,
                    146
                ],
                "state_rot": 0,
                "up_down": 0
            },
            {
                "base_action": 0,
                "grasp_drop": 0,
                "mode": 3,
                "state_ee": [
                    117,
                    121,
                    146
                ],
                "state_rot": 0,
                "up_down": 0
            },
            {
                "base_action": 0,
                "grasp_drop": 0,
                "mode": 3,
                "state_ee": [
                    117,
                    121,
                    146
                ],
                "state_rot": 0,
                "up_down": 0
            },
            {
                "base_action": 0,
                "grasp_drop": 0,
                "mode": 3,
                "state_ee": [
                    117,
                    121,
                    146
                ],
                "state_rot": 0,
                "up_down": 0
            },
            {
                "base_action": 0,
                "grasp_drop": 0,
                "mode": 3,
                "state_ee": [
                    117,
                    121,
                    146
                ],
                "state_rot": 0,
                "up_down": 0
            },
            {
                "base_action": 0,
                "grasp_drop": 0,
                "mode": 3,
                "state_ee": [
                    117,
                    121,
                    146
                ],
                "state_rot": 0,
                "up_down": 0
            },
            {
                "base_action": 0,
                "grasp_drop": 0,
                "mode": 2,
                "state_ee": [
                    0,
                    0,
                    0
                ],
                "state_rot": [
                    133
                ],
                "up_down": 0
            },
            {
                "base_action": 0,
                "grasp_drop": 0,
                "mode": 3,
                "state_ee": [
                    89,
                    140,
                    217
                ],
                "state_rot": 0,
                "up_down": 0
            },
            {
                "base_action": 0,
                "grasp_drop": 0,
                "mode": 3,
                "state_ee": [
                    117,
                    121,
                    146
                ],
                "state_rot": 0,
                "up_down": 0
            },
            {
                "base_action": 0,
                "grasp_drop": 0,
                "mode": 2,
                "state_ee": [
                    0,
                    0,
                    0
                ],
                "state_rot": [
                    121
                ],
                "up_down": 0
            },
            {
                "base_action": 1,
                "grasp_drop": 0,
                "mode": 1,
                "state_ee": [
                    0,
                    0,
                    0
                ],
                "state_rot": 0,
                "up_down": 0
            },
            {
                "base_action": 0,
                "grasp_drop": 0,
                "mode": 3,
                "state_ee": [
                    117,
                    121,
                    146
                ],
                "state_rot": 0,
                "up_down": 0
            },
            {
                "base_action": 0,
                "grasp_drop": 0,
                "mode": 3,
                "state_ee": [
                    117,
                    121,
                    146
                ],
                "state_rot": 0,
                "up_down": 0
            },
            {
                "base_action": 0,
                "grasp_drop": 0,
                "mode": 3,
                "state_ee": [
                    117,
                    121,
                    146
                ],
                "state_rot": 0,
                "up_down": 0
            },
            {
                "base_action": 0,
                "grasp_drop": 0,
                "mode": 3,
                "state_ee": [
                    117,
                    116,
                    146
                ],
                "state_rot": 0,
                "up_down": 0
            },
            {
                "base_action": 0,
                "grasp_drop": 0,
                "mode": 3,
                "state_ee": [
                    117,
                    116,
                    146
                ],
                "state_rot": 0,
                "up_down": 0
            },
            {
                "base_action": 0,
                "grasp_drop": 0,
                "mode": 3,
                "state_ee": [
                    117,
                    116,
                    146
                ],
                "state_rot": 0,
                "up_down": 0
            },
            {
                "base_action": 0,
                "grasp_drop": 0,
                "mode": 2,
                "state_ee": [
                    0,
                    0,
                    0
                ],
                "state_rot": [
                    133
                ],
                "up_down": 0
            },
            {
                "base_action": 0,
                "grasp_drop": 0,
                "mode": 3,
                "state_ee": [
                    86,
                    146,
                    218
                ],
                "state_rot": 0,
                "up_down": 0
            },
            {
                "base_action": 0,
                "grasp_drop": 0,
                "mode": 3,
                "state_ee": [
                    117,
                    121,
                    146
                ],
                "state_rot": 0,
                "up_down": 0
            },
            {
                "base_action": 0,
                "grasp_drop": 0,
                "mode": 3,
                "state_ee": [
                    117,
                    121,
                    146
                ],
                "state_rot": 0,
                "up_down": 0
            },
            {
                "base_action": 0,
                "grasp_drop": 0,
                "mode": 3,
                "state_ee": [
                    117,
                    116,
                    146
                ],
                "state_rot": 0,
                "up_down": 0
            },
            {
                "base_action": 0,
                "grasp_drop": 0,
                "mode": 3,
                "state_ee": [
                    117,
                    116,
                    146
                ],
                "state_rot": 0,
                "up_down": 0
            },
            {
                "base_action": 0,
                "grasp_drop": 0,
                "mode": 3,
                "state_ee": [
                    117,
                    116,
                    146
                ],
                "state_rot": 0,
                "up_down": 0
            },
            {
                "base_action": 0,
                "grasp_drop": 0,
                "mode": 3,
                "state_ee": [
                    117,
                    121,
                    146
                ],
                "state_rot": 0,
                "up_down": 0
            },
            {
                "base_action": 0,
                "grasp_drop": 0,
                "mode": 3,
                "state_ee": [
                    117,
                    121,
                    146
                ],
                "state_rot": 0,
                "up_down": 0
            },
            {
                "base_action": 0,
                "grasp_drop": 0,
                "mode": 3,
                "state_ee": [
                    117,
                    116,
                    146
                ],
                "state_rot": 0,
                "up_down": 0
            },
            {
                "base_action": 0,
                "grasp_drop": 0,
                "mode": 3,
                "state_ee": [
                    117,
                    116,
                    146
                ],
                "state_rot": 0,
                "up_down": 0
            },
            {
                "base_action": 2,
                "grasp_drop": 0,
                "mode": 1,
                "state_ee": [
                    0,
                    0,
                    0
                ],
                "state_rot": 0,
                "up_down": 0
            },
            {
                "base_action": 0,
                "grasp_drop": 0,
                "mode": 3,
                "state_ee": [
                    84,
                    141,
                    221
                ],
                "state_rot": 0,
                "up_down": 0
            },
            {
                "base_action": 0,
                "grasp_drop": 0,
                "mode": 3,
                "state_ee": [
                    117,
                    120,
                    146
                ],
                "state_rot": 0,
                "up_down": 0
            },
            {
                "base_action": 0,
                "grasp_drop": 0,
                "mode": 3,
                "state_ee": [
                    117,
                    121,
                    146
                ],
                "state_rot": 0,
                "up_down": 0
            },
            {
                "base_action": 0,
                "grasp_drop": 0,
                "mode": 3,
                "state_ee": [
                    117,
                    121,
                    146
                ],
                "state_rot": 0,
                "up_down": 0
            },
            {
                "base_action": 0,
                "grasp_drop": 0,
                "mode": 3,
                "state_ee": [
                    117,
                    116,
                    146
                ],
                "state_rot": 0,
                "up_down": 0
            },
            {
                "base_action": 0,
                "grasp_drop": 0,
                "mode": 3,
                "state_ee": [
                    117,
                    116,
                    146
                ],
                "state_rot": 0,
                "up_down": 0
            },
            {
                "base_action": 0,
                "grasp_drop": 0,
                "mode": 3,
                "state_ee": [
                    117,
                    117,
                    146
                ],
                "state_rot": 0,
                "up_down": 0
            },
            {
                "base_action": 0,
                "grasp_drop": 0,
                "mode": 3,
                "state_ee": [
                    117,
                    120,
                    146
                ],
                "state_rot": 0,
                "up_down": 0
            },
            {
                "base_action": 0,
                "grasp_drop": 0,
                "mode": 3,
                "state_ee": [
                    117,
                    121,
                    146
                ],
                "state_rot": 0,
                "up_down": 0
            },
            {
                "base_action": 0,
                "grasp_drop": 0,
                "mode": 3,
                "state_ee": [
                    117,
                    116,
                    146
                ],
                "state_rot": 0,
                "up_down": 0
            },
            {
                "base_action": 2,
                "grasp_drop": 0,
                "mode": 1,
                "state_ee": [
                    0,
                    0,
                    0
                ],
                "state_rot": 0,
                "up_down": 0
            },
            {
                "base_action": 0,
                "grasp_drop": 0,
                "mode": 3,
                "state_ee": [
                    81,
                    141,
                    224
                ],
                "state_rot": 0,
                "up_down": 0
            },
            {
                "base_action": 0,
                "grasp_drop": 0,
                "mode": 3,
                "state_ee": [
                    117,
                    120,
                    146
                ],
                "state_rot": 0,
                "up_down": 0
            },
            {
                "base_action": 0,
                "grasp_drop": 0,
                "mode": 3,
                "state_ee": [
                    117,
                    121,
                    146
                ],
                "state_rot": 0,
                "up_down": 0
            },
            {
                "base_action": 0,
                "grasp_drop": 0,
                "mode": 3,
                "state_ee": [
                    117,
                    121,
                    146
                ],
                "state_rot": 0,
                "up_down": 0
            },
            {
                "base_action": 0,
                "grasp_drop": 0,
                "mode": 3,
                "state_ee": [
                    117,
                    116,
                    146
                ],
                "state_rot": 0,
                "up_down": 0
            },
            {
                "base_action": 0,
                "grasp_drop": 0,
                "mode": 3,
                "state_ee": [
                    117,
                    116,
                    146
                ],
                "state_rot": 0,
                "up_down": 0
            },
            {
                "base_action": 0,
                "grasp_drop": 0,
                "mode": 3,
                "state_ee": [
                    117,
                    117,
                    146
                ],
                "state_rot": 0,
                "up_down": 0
            },
            {
                "base_action": 0,
                "grasp_drop": 0,
                "mode": 3,
                "state_ee": [
                    117,
                    120,
                    146
                ],
                "state_rot": 0,
                "up_down": 0
            },
            {
                "base_action": 0,
                "grasp_drop": 0,
                "mode": 3,
                "state_ee": [
                    117,
                    121,
                    146
                ],
                "state_rot": 0,
                "up_down": 0
            },
            {
                "base_action": 0,
                "grasp_drop": 0,
                "mode": 3,
                "state_ee": [
                    117,
                    116,
                    146
                ],
                "state_rot": 0,
                "up_down": 0
            },
            {
                "base_action": 1,
                "grasp_drop": 0,
                "mode": 1,
                "state_ee": [
                    0,
                    0,
                    0
                ],
                "state_rot": 0,
                "up_down": 0
            },
            {
                "base_action": 0,
                "grasp_drop": 0,
                "mode": 3,
                "state_ee": [
                    84,
                    141,
                    221
                ],
                "state_rot": 0,
                "up_down": 0
            },
            {
                "base_action": 2,
                "grasp_drop": 0,
                "mode": 1,
                "state_ee": [
                    0,
                    0,
                    0
                ],
                "state_rot": 0,
                "up_down": 0
            },
            {
                "base_action": 0,
                "grasp_drop": 0,
                "mode": 3,
                "state_ee": [
                    117,
                    112,
                    146
                ],
                "state_rot": 0,
                "up_down": 0
            },
            {
                "base_action": 0,
                "grasp_drop": 0,
                "mode": 3,
                "state_ee": [
                    117,
                    116,
                    146
                ],
                "state_rot": 0,
                "up_down": 0
            },
            {
                "base_action": 0,
                "grasp_drop": 0,
                "mode": 3,
                "state_ee": [
                    117,
                    121,
                    146
                ],
                "state_rot": 0,
                "up_down": 0
            },
            {
                "base_action": 1,
                "grasp_drop": 0,
                "mode": 1,
                "state_ee": [
                    0,
                    0,
                    0
                ],
                "state_rot": 0,
                "up_down": 0
            },
            {
                "base_action": 0,
                "grasp_drop": 0,
                "mode": 3,
                "state_ee": [
                    117,
                    121,
                    146
                ],
                "state_rot": 0,
                "up_down": 0
            },
            {
                "base_action": 0,
                "grasp_drop": 0,
                "mode": 3,
                "state_ee": [
                    117,
                    121,
                    146
                ],
                "state_rot": 0,
                "up_down": 0
            },
            {
                "base_action": 0,
                "grasp_drop": 0,
                "mode": 3,
                "state_ee": [
                    117,
                    121,
                    146
                ],
                "state_rot": 0,
                "up_down": 0
            },
            {
                "base_action": 0,
                "grasp_drop": 0,
                "mode": 3,
                "state_ee": [
                    117,
                    116,
                    146
                ],
                "state_rot": 0,
                "up_down": 0
            },
            {
                "base_action": 0,
                "grasp_drop": 0,
                "mode": 0,
                "state_ee": [
                    0,
                    0,
                    0
                ],
                "state_rot": [
                    0
                ],
                "up_down": 0
            }
        ],
        "lang_goal": [
            3,
            58,
            5,
            59,
            26,
            37,
            5,
            60,
            43,
            4,
            5,
            61,
            62,
            23,
            19,
            44,
            3,
            63,
            47,
            5,
            56,
            42,
            12,
            64,
            14,
            27,
            61,
            29,
            5,
            65,
            66,
            67,
            5,
            68,
            69,
            19,
            2
        ]
    },
    "root": "data/feats_discrete_relative_extra/data_16:03:07",
    "scene": "FloorPlan_Train12_3",
    "split": "train"
}